mep_api/__init__.py
mep_api/euparty_abreviations.json
mep_api-0.1.2.dist-info/LICENSE
mep_api-0.1.2.dist-info/METADATA
mep_api-0.1.2.dist-info/WHEEL
mep_api-0.1.2.dist-info/top_level.txt
mep_api-0.1.2.dist-info/RECORD
