Metadata-Version: 2.1
Name: mep-api
Version: 0.1.2
Summary: A web scraping package for data on members of the European Parliament.
Home-page: http://www.github.com/mgutmann/mep_api
Author: Michel Gutmann
Author-email: mich.gutmann@gmail.com
License: MIT
Platform: UNKNOWN
Requires-Python: >=3.7
License-File: LICENSE
Requires-Dist: requests
Requires-Dist: beautifulsoup4
Requires-Dist: tqdm
